sticker_convert/__init__.py
sticker_convert/__main__.py
sticker_convert/cli.py
sticker_convert/converter.py
sticker_convert/definitions.py
sticker_convert/gui.py
sticker_convert/job.py
sticker_convert/job_option.py
sticker_convert/py.typed
sticker_convert/version.py
sticker_convert/auth/__init__.py
sticker_convert/auth/auth_base.py
sticker_convert/auth/auth_discord.py
sticker_convert/auth/auth_kakao_android_login.py
sticker_convert/auth/auth_kakao_desktop_login.py
sticker_convert/auth/auth_kakao_desktop_memdump.py
sticker_convert/auth/auth_line.py
sticker_convert/auth/auth_signal.py
sticker_convert/auth/auth_telethon.py
sticker_convert/auth/auth_viber.py
sticker_convert/auth/telegram_api.py
sticker_convert/downloaders/__init__.py
sticker_convert/downloaders/download_band.py
sticker_convert/downloaders/download_base.py
sticker_convert/downloaders/download_discord.py
sticker_convert/downloaders/download_kakao.py
sticker_convert/downloaders/download_line.py
sticker_convert/downloaders/download_ogq.py
sticker_convert/downloaders/download_signal.py
sticker_convert/downloaders/download_telegram.py
sticker_convert/downloaders/download_viber.py
sticker_convert/gui_components/__init__.py
sticker_convert/gui_components/gui_utils.py
sticker_convert/gui_components/frames/__init__.py
sticker_convert/gui_components/frames/comp_frame.py
sticker_convert/gui_components/frames/config_frame.py
sticker_convert/gui_components/frames/control_frame.py
sticker_convert/gui_components/frames/cred_frame.py
sticker_convert/gui_components/frames/input_frame.py
sticker_convert/gui_components/frames/output_frame.py
sticker_convert/gui_components/frames/progress_frame.py
sticker_convert/gui_components/frames/right_clicker.py
sticker_convert/gui_components/windows/__init__.py
sticker_convert/gui_components/windows/advanced_compression_window.py
sticker_convert/gui_components/windows/base_window.py
sticker_convert/gui_components/windows/discord_get_auth_window.py
sticker_convert-2.18.2.0.dist-info/licenses/LICENSE
sticker_convert-2.18.2.0.dist-info/METADATA
sticker_convert-2.18.2.0.dist-info/WHEEL
sticker_convert-2.18.2.0.dist-info/entry_points.txt
sticker_convert-2.18.2.0.dist-info/top_level.txt
sticker_convert-2.18.2.0.dist-info/RECORD
