Metadata-Version: 2.4
Name: sticker-convert
Version: 2.18.2.0
Summary: Convert (animated) stickers to/from WhatsApp, Telegram, Signal, Line, Kakao, Viber, Discord, iMessage. Written in Python.
Author-email: laggykiller <chaudominic2@gmail.com>
Maintainer-email: laggykiller <chaudominic2@gmail.com>
License:                     GNU GENERAL PUBLIC LICENSE
Project-URL: Homepage, https://github.com/laggykiller/sticker-convert
Project-URL: Source, https://github.com/laggykiller/sticker-convert
Project-URL: Documentation, https://github.com/laggykiller/sticker-convert
Project-URL: Tracker, https://github.com/laggykiller/sticker-convert/issues
Project-URL: Repository, https://github.com/laggykiller/sticker-convert
Keywords: telegram,line,tgs,whatsapp,kakao,signal,imessage,wastickers,viber,discord
Classifier: Development Status :: 5 - Production/Stable
Classifier: Intended Audience :: End Users/Desktop
Classifier: Topic :: Multimedia :: Graphics :: Graphics Conversion
Classifier: License :: OSI Approved :: GNU General Public License v2 (GPLv2)
Classifier: Programming Language :: Python :: 3
Classifier: Programming Language :: Python :: 3.10
Classifier: Programming Language :: Python :: 3.11
Classifier: Programming Language :: Python :: 3.12
Classifier: Programming Language :: Python :: 3 :: Only
Requires-Python: >=3.10
License-File: LICENSE
Requires-Dist: aiolimiter~=1.2.1
Requires-Dist: anyio~=4.12.1
Requires-Dist: apngasm_python~=1.3.2
Requires-Dist: av~=16.1.0
Requires-Dist: beautifulsoup4~=4.14.3
Requires-Dist: cryptg~=0.5.2
Requires-Dist: cryptography~=46.0.3
Requires-Dist: rookiepy~=0.5.6
Requires-Dist: httpx~=0.28.1
Requires-Dist: imagequant~=1.1.4
Requires-Dist: memory-tempfile~=2.2.3
Requires-Dist: mergedeep~=1.3.4
Requires-Dist: numpy>=1.22.4
Requires-Dist: Pillow~=12.1.0
Requires-Dist: pyoxipng~=9.1.1
Requires-Dist: python-telegram-bot~=22.5
Requires-Dist: pyuegc~=16.0.3
Requires-Dist: psutil~=7.2.1
Requires-Dist: PyMemoryEditor~=1.6.0
Requires-Dist: requests~=2.32.4
Requires-Dist: rlottie_python~=1.3.8
Requires-Dist: signalstickers-client-fork-laggykiller~=3.3.0.post2
Requires-Dist: socksio~=1.0.0
Requires-Dist: telethon~=1.42.0
Requires-Dist: tqdm~=4.67.1
Requires-Dist: ttkbootstrap-fork-laggykiller~=1.5.1
Requires-Dist: websocket_client~=1.9.0
Dynamic: license-file
